[
  {
    "order": 1,
    "name": {
      "uz": "Yanvar",
      "en": "January"
    },
    "days": 31
  },
  {
    "order": 2,
    "name": {
      "uz": "Fevral",
      "en": "February"
    },
    "linkedWithLeap": true,
    "days": 28
  },
  {
    "order": 3,
    "name": {
      "uz": "Mart",
      "en": "March"
    },
    "days": 31
  },
  {
    "order": 4,
    "name": {
      "uz": "Aprel",
      "en": "April"
    },
    "days": 30
  },
  {
    "order": 5,
    "name": {
      "uz": "May",
      "en": "May"
    },
    "days": 31
  },
  {
    "order": 6,
    "name": {
      "uz": "Iyun",
      "en": "June"
    },
    "days": 30
  },
  {
    "order": 7,
    "name": {
      "uz": "Iyul",
      "en": "July"
    },
    "days": 31
  },
  {
    "order": 8,
    "name": {
      "uz": "Avgust",
      "en": "August"
    },
    "days": 31
  },
  {
    "order": 9,
    "name": {
      "uz": "Sentabr",
      "en": "September"
    },
    "days": 30
  },
  {
    "order": 10,
    "name": {
      "uz": "Oktabr",
      "en": "October"
    },
    "days": 31
  },
  {
    "order": 11,
    "name": {
      "uz": "Noyabr",
      "en": "November"
    },
    "days": 30
  },
  {
    "order": 12,
    "name": {
      "uz": "Dekabr",
      "en": "December"
    },
    "days": 31
  }
]
